LICENSE
README.md
setup.cfg
setup.py
csv_plot/__init__.py
csv_plot/background_processor.py
csv_plot/entrypoint.py
csv_plot/fast_pad_and_sample.c
csv_plot/interfaces.py
csv_plot.egg-info/PKG-INFO
csv_plot.egg-info/SOURCES.txt
csv_plot.egg-info/dependency_links.txt
csv_plot.egg-info/entry_points.txt
csv_plot.egg-info/requires.txt
csv_plot.egg-info/top_level.txt
csv_plot/csv/__init__.py
csv_plot/csv/gettable.py
csv_plot/csv/pad_and_sample.py
csv_plot/csv/padded_csv_file.py
csv_plot/csv/padded_text_file.py
csv_plot/csv/selector.py
csv_plot/csv/sorted_padded_csv_file.py
csv_plot/csv/splitted_gettable.py
csv_plot/csv/tests/__init__.py
csv_plot/csv/tests/test_pad_and_sample.py
csv_plot/csv/tests/test_padded_csv_file.py
csv_plot/csv/tests/test_padded_text_file.py
csv_plot/csv/tests/test_selector.py
csv_plot/csv/tests/test_sorted_padded_csv_file.py
csv_plot/csv/tests/test_splitted_gettable.py
csv_plot/csv/tests/test_splitted_padded_text_file.py
csv_plot/csv/tests/assets/__init__.py