Metadata-Version: 2.1
Name: csv-plot
Version: 0.1.2
Summary: CSV Plot - Plot CSV files without headaches!
Home-page: https://nalepae.github.io/csv-plot
Author: Manu NALEPA
Author-email: nalepae@gmail.com
License: BSD-3-Clause
Platform: any
Classifier: License :: OSI Approved :: BSD License
Classifier: Operating System :: OS Independent
Classifier: Programming Language :: Python
Classifier: Programming Language :: Python :: 3
Classifier: Programming Language :: Python :: 3 :: Only
Classifier: Topic :: Scientific/Engineering
Provides-Extra: dev
License-File: LICENSE
